django_gsheets2/__init__.py
django_gsheets2/gsheets/__init__.py
django_gsheets2/gsheets/admin.py
django_gsheets2/gsheets/apps.py
django_gsheets2/gsheets/auth.py
django_gsheets2/gsheets/decorators.py
django_gsheets2/gsheets/gsheets.py
django_gsheets2/gsheets/management/__init__.py
django_gsheets2/gsheets/management/commands/__init__.py
django_gsheets2/gsheets/management/commands/syncgsheets.py
django_gsheets2/gsheets/migrations/0001_initial.py
django_gsheets2/gsheets/migrations/0002_accesscredentials_created_time.py
django_gsheets2/gsheets/migrations/0003_alter_accesscredentials_id.py
django_gsheets2/gsheets/migrations/__init__.py
django_gsheets2/gsheets/mixins.py
django_gsheets2/gsheets/models.py
django_gsheets2/gsheets/settings.py
django_gsheets2/gsheets/signals/__init__.py
django_gsheets2/gsheets/tests.py
django_gsheets2/gsheets/urls.py
django_gsheets2/gsheets/views.py
django_gsheets2-0.1.0.dist-info/METADATA
django_gsheets2-0.1.0.dist-info/WHEEL
django_gsheets2-0.1.0.dist-info/RECORD
